emb_opt/__init__.py
emb_opt/_modidx.py
emb_opt/data_source.py
emb_opt/executor.py
emb_opt/filter.py
emb_opt/imports.py
emb_opt/log.py
emb_opt/module.py
emb_opt/prune.py
emb_opt/runner.py
emb_opt/schemas.py
emb_opt/score.py
emb_opt/update.py
emb_opt/utils.py
emb_opt/plugins/__init__.py
emb_opt/plugins/faiss.py
emb_opt/plugins/huggingface.py
emb_opt/plugins/qdrant.py
emb_opt-1.0.2.dist-info/LICENSE
emb_opt-1.0.2.dist-info/METADATA
emb_opt-1.0.2.dist-info/WHEEL
emb_opt-1.0.2.dist-info/entry_points.txt
emb_opt-1.0.2.dist-info/top_level.txt
emb_opt-1.0.2.dist-info/RECORD
